{
    "MQ_ENDPOINTS" : [
        {
            "QMGR" : "<your qm>",
            "MQ_REST_HOST" : "https://<your mq server>",
            "MQ_REST_PORT" : "9443",
            "ADMIN_USER" : "<your admin user",
            "ADMIN_PASSWORD" : "<your admin password"
        }
    ],
    "COS_STORAGE" : {
        "bucket": "mq-ce-observer",
        "object_key": "storeddata", 
        "cos_apikey": "<api key goes here",
        "endpoints": "<cos endpoint goes here>",
        "resource_instance_id": "<cos instance id goes here>"
    },
    "CODE_ENGINE" : {
        "ce_apikey": "<api key goes here",  
        "regions" :[
            {"region": "<region1 goes here>"},
            {"region": "<region2 goes here>"}
        ] 
    }
}
