{
    "directions": [
        "Place the almonds in a food processor. Process on high until ground almonds begin to form a ball. Drizzle olive oil over almonds and continue to process, stopping occasionally to scrape sides of the bowl with a spatula as needed. Store in an airtight container."
    ],
    "ingredients": [
        "1 cup toasted almonds",
        "2 teaspoons olive oil"
    ],
    "language": "en-US",
    "source": "allrecipes.com",
    "tags": [],
    "title": "Almond Butter",
    "url": "http://allrecipes.com/recipe/145449/almond-butter/"
}
