{
    "directions": [
        "Preheat the oven to 425 degrees F (220 degrees C). Grease a shallow baking dish.",
        "Season chicken breasts. Coat chicken on all sides with mayonnaise, and roll in bread crumbs until coated. Place coated breasts into the prepared pan.",
        "Bake uncovered for 30 minutes in the preheated oven, or until chicken is no longer pink in the middle and the juices run clear."
    ],
    "ingredients": [
        "4 skinless, boneless chicken breast halves",
        "salt and pepper to taste",
        "1/2 cup mayonnaise",
        "2 cups Italian seasoned bread crumbs"
    ],
    "language": "en-US",
    "source": "allrecipes.com",
    "tags": [],
    "title": "Amazing Chicken",
    "url": "http://allrecipes.com/recipe/55872/amazing-chicken/"
}
