{
    "directions": [
        "Peel potatoes and cut into 1-inch pieces.",
        "In a steamer set over boiling water steam potatoes, covered, until very tender, 15 to 20 minutes.",
        "In a large heavy saucepan cook onion in 4 tablespoons butter over moderately low heat, stirring, until softened. Add anchovies and cook, mashing them, until they dissolve, about 1 minute. Stir in milk, cream, and remaining 2 tablespoons butter and heat until hot but not boiling.",
        "Force potatoes through a ricer or food mill into pan and stir until smooth. Stir in chives and salt and pepper to taste."
    ],
    "ingredients": [
        "6 large russet (baking) potatoes (about 3 1/2 pounds)",
        "1 onion, chopped fine",
        "3/4 stick (6 tablespoons) unsalted butter",
        "8 flat anchovies, rinsed, patted dry, and minced",
        "3/4 cup milk",
        "1/4 cup heavy cream",
        "1/4 cup thinly sliced fresh chives or scallion greens"
    ],
    "language": "en-US",
    "source": "www.epicurious.com",
    "tags": [
        "Milk/Cream",
        "Fish",
        "Herb",
        "Potato",
        "Side",
        "Quick & Easy",
        "Winter",
        "Gourmet",
        "Pescatarian",
        "Wheat/Gluten-Free",
        "Peanut Free",
        "Tree Nut Free",
        "Soy Free",
        "No Sugar Added",
        "Kosher"
    ],
    "title": "Anchovy Mashed Potatoes",
    "url": "http://www.epicurious.com/recipes/food/views/anchovy-mashed-potatoes-11639"
}
