{
    "directions": [
        "Combine vodka, simple syrup, tea, and lime juice in a blender and freeze 3\u201312 hours (mixture will be partially frozen).",
        "Add 2 cups ice to mixture and blend until thick and smooth. Divide among glasses and garnish with mint sprigs."
    ],
    "ingredients": [
        "6 ounces vodka",
        "5 ounces simple syrup",
        "4 ounces chilled brewed black tea",
        "3 ounces fresh lime juice",
        "Mint sprigs (for serving)"
    ],
    "language": "en-US",
    "source": "www.epicurious.com",
    "tags": [
        "Freeze/Chill",
        "Cocktail",
        "Vodka",
        "Lime Juice",
        "Tea",
        "Iced Tea",
        "Summer",
        "Drinks"
    ],
    "title": "Arnie\u2019s Gimlet Slush",
    "url": "http://www.epicurious.com/recipes/food/views/arnies-gimlet-slush"
}
