{
    "directions": [
        "Pour milk into a large microwave-safe container; heat in microwave until warmed, 1 to 2 minutes.",
        "Stir sweetener and cocoa powder into the warmed milk to dissolve completely.",
        "Froth the milk according to your espresso machine's directions.",
        "Stir espresso into the frothed milk mixture."
    ],
    "ingredients": [
        "1 1/2 cups milk",
        "3 packets granular no-calorie sucralose sweetener (such as Splenda\u00ae)",
        "1 tablespoon cocoa powder",
        "4 shots fresh brewed espresso"
    ],
    "language": "en-US",
    "source": "allrecipes.com",
    "tags": [],
    "title": "Azucena's Homemade Mocha",
    "url": "http://allrecipes.com/recipe/240772/azucenas-homemade-mocha/"
}
