{
    "directions": [
        "Carefully pour coffee liqueur, Grand Marnier, and Irish cream liqueur into a cordial glass so that they do not mix."
    ],
    "ingredients": [
        "1 tablespoon Kahlua or other coffee flavored liqueur",
        "1 tablespoon brandy-based orange liqueur (such as Grand Marnier\u00ae)",
        "1 tablespoon Irish cream liqueur"
    ],
    "language": "en-US",
    "source": "allrecipes.com",
    "tags": [],
    "title": "B-52 Bomber",
    "url": "http://allrecipes.com/recipe/51819/b-52-bomber/"
}
