{
    "directions": [
        "Preheat oven to 400\u00b0F. Butter rimmed baking sheet. Arrange fish on prepared sheet; sprinkle with salt and pepper. Combine spinach souffl, nuts, onions, garlic and lemon peel in medium bowl; stir to blend well. Spoon topping over fish. Sprinkle with cheese.",
        "Bake fish until just opaque in center, about 15 minutes. Transfer fish to plates."
    ],
    "ingredients": [
        "6 6- to 7-ounce sea bass or orange roughy fillets",
        "1 12-ounce package frozen spinach souffl\u00e9, thawed",
        "1/2 cup pine nuts, toasted",
        "3 green onions, finely chopped",
        "2 garlic cloves, minced",
        "2 teaspoons grated lemon peel",
        "1/2 cup grated Parmesan cheese"
    ],
    "language": "en-US",
    "source": "www.epicurious.com",
    "tags": [
        "Cheese",
        "Dairy",
        "Fish",
        "Leafy Green",
        "Nut",
        "Vegetable",
        "Bake",
        "Dinner",
        "Parmesan",
        "Pine Nut",
        "Seafood",
        "Bass",
        "Spinach",
        "Spring",
        "Summer",
        "Florida",
        "Sugar Conscious",
        "Pescatarian",
        "Wheat/Gluten-Free",
        "Peanut Free",
        "Soy Free",
        "No Sugar Added",
        "Kosher"
    ],
    "title": "Baked Fish Fillets with Spinach-Pine Nut Topping",
    "url": "http://www.epicurious.com/recipes/food/views/baked-fish-fillets-with-spinach-pine-nut-topping-103756"
}
