{
    "directions": [
        "Using stems as a handle, slice beets paper-thin with slicer (wear protective gloves to avoid staining hands). Toss with vinegar and 1/4 teaspoon salt in a bowl, then let stand 5 minutes to wilt.",
        "Divide beets among 4 large plates, overlapping slices slightly. Top with goat cheese.",
        "Toss arugula and endive with 1 tablespoon oil and salt and pepper to taste, then mound over goat cheese. Drizzle beets with remaining 2 tablespoons oil."
    ],
    "ingredients": [
        "3 medium beets, peeled and stems trimmed to 2 inches",
        "1 1/2 tablespoons red-wine vinegar",
        "4 ounces goat cheese, sliced",
        "4 ounces baby arugula (4 cups packed)",
        "1 large Belgian endive, thickly sliced crosswise",
        "3 tablespoons extra-virgin olive oil",
        "Equipment: an adjustable-blade slicer"
    ],
    "language": "en-US",
    "source": "www.epicurious.com",
    "tags": [
        "Salad",
        "Vegetable",
        "Side",
        "No-Cook",
        "Vegetarian",
        "Quick & Easy",
        "Lunch",
        "Goat Cheese",
        "Arugula",
        "Beet",
        "Summer",
        "Gourmet",
        "Pescatarian",
        "Wheat/Gluten-Free",
        "Peanut Free",
        "Tree Nut Free",
        "Soy Free",
        "No Sugar Added",
        "Kosher"
    ],
    "title": "Beet Carpaccio with Goat Cheese and Arugula",
    "url": "http://www.epicurious.com/recipes/food/views/beet-carpaccio-with-goat-cheese-and-arugula-239246"
}
