{
    "directions": [
        "Combine all ingredients in blender. Blend until thick and smooth, about 2 minutes. Pour into 2 large glasses and serve immediately."
    ],
    "ingredients": [
        "cup frozen unsweetened raspberries",
        "1 cup frozen unsweetened blackberries",
        "1 8-ounce container vanilla yogurt",
        "1 cup reduced-fat (2%) milk",
        "3 tablespoons honey",
        "1 teaspoon grated orange peel",
        "1 teaspoon vanilla extract",
        "Large pinch of ground cinnamon"
    ],
    "language": "en-US",
    "source": "www.epicurious.com",
    "tags": [
        "Milk/Cream",
        "Non-Alcoholic",
        "Blender",
        "Yogurt",
        "Blackberry",
        "Raspberry",
        "Orange",
        "Vanilla",
        "Summer",
        "Honey",
        "Cinnamon",
        "Drink"
    ],
    "title": "Berry-Yogurt Smoothie",
    "url": "http://www.epicurious.com/recipes/food/views/berry-yogurt-smoothie-201222"
}
