{
    "directions": [
        "In a medium bowl, mix mayonnaise, sour cream, green onions, dried parsley, blue cheese and garlic salt. Cover and chill in the refrigerator until serving."
    ],
    "ingredients": [
        "1 cup mayonnaise",
        "1 cup sour cream",
        "4 green onions, finely chopped",
        "2 tablespoons dried parsley",
        "4 ounces blue cheese, crumbled",
        "garlic salt to taste"
    ],
    "language": "en-US",
    "source": "allrecipes.com",
    "tags": [],
    "title": "Blue Cheese Dip II",
    "url": "http://allrecipes.com/recipe/24901/blue-cheese-dip-ii/"
}
