{
    "directions": [
        "Melt half the butter in a Dutch oven or heavy pot on medium heat. Add onion and garlic and cook, stirring occasionally, for 5 minutes.",
        "Cut chicken into bite-sized chunks. Sprinkle with salt and pepper. Increase heat to medium high. Brown chicken. Add curry paste, ginger and cinnamon and cook, stirring for 30 seconds. Add tomatoes, including juices, and remaining butter to pan and bring to boil.",
        "Reduce heat and simmer, covered, for 20 minutes or until chicken is cooked through. Stir in sour cream and coriander.",
        "Heat until very hot without boiling. Serve with rice or naan bread. Garnish with lime wedges."
    ],
    "image": "https://www.allrecipes.com/img/misc/og-default.png",
    "ingredients": [
        "\u00bd cup Gay Lea Spreadables Regular",
        "2  onions, peeled and sliced",
        "3  garlic cloves, minced",
        "2 pounds skinless, boneless chicken breast",
        "\u00bd teaspoon salt",
        "\u00bd teaspoon pepper",
        "4 teaspoons mild Indian curry paste",
        "2 teaspoons ginger, minced",
        "1 teaspoon ground cinnamon",
        "1 (28 ounce) can diced tomatoes",
        "\u00bc cup Gay Lea Regular Sour Cream",
        "\u00bc cup chopped fresh coriander",
        "Steamed rice or naan bread (optional)",
        "Lime wedges (optional)"
    ],
    "language": "en-US",
    "source": "allrecipes.com",
    "tags": [],
    "title": "Bombay Butter Chicken",
    "url": "http://allrecipes.com/recipe/241581/bombay-butter-chicken/"
}