{
    "directions": [
        "Stir bourbon, triple sec, lime juice, simple syrup, and club soda together in a cocktail shaker. Fill a glass with ice and pour cocktail over ice."
    ],
    "ingredients": [
        "1 (1.5 fluid ounce) jigger Kentucky bourbon",
        "1/2 (1.5 fluid ounce) jigger triple sec",
        "1/2 (1.5 fluid ounce) jigger Key lime juice",
        "1 splash simple syrup, or to taste",
        "1 splash club soda, or to taste",
        "ice"
    ],
    "language": "en-US",
    "source": "allrecipes.com",
    "tags": [],
    "title": "Bourbon Kamikaze",
    "url": "http://allrecipes.com/recipe/238186/bourbon-kamikaze/"
}
